<?xml version="1.0" encoding="UTF-8"?><record_update table="sp_instance_link">
    <sp_instance_link action="DELETE">
        <active>true</active>
        <class_name/>
        <color>default</color>
        <css/>
        <glyph>keyboard-o</glyph>
        <id/>
        <kb_article/>
        <kb_category/>
        <kb_topic/>
        <order>1</order>
        <roles/>
        <sc_cat_item/>
        <sc_category/>
        <short_description/>
        <size>md</size>
        <sp_column display_value="1">27c2580cdb9e509099b092d8db96192b</sp_column>
        <sp_page/>
        <sp_widget display_value="Icon Link">3caa67afcb13020000f8d856634c9c2e</sp_widget>
        <sys_class_name>sp_instance_link</sys_class_name>
        <sys_created_by>admin</sys_created_by>
        <sys_created_on>2020-07-21 08:16:50</sys_created_on>
        <sys_id>2fa42947db865c5099b092d8db9619e0</sys_id>
        <sys_mod_count>5</sys_mod_count>
        <sys_name>Keyboard/Mouse issue</sys_name>
        <sys_package display_value="Coach Incident  optimization" source="x_achin_coach_inci">2b20d4e8db87f3404f229a64db96199d</sys_package>
        <sys_policy/>
        <sys_scope display_value="Coach Incident  optimization">2b20d4e8db87f3404f229a64db96199d</sys_scope>
        <sys_update_name>sp_instance_link_2fa42947db865c5099b092d8db9619e0</sys_update_name>
        <sys_updated_by>admin</sys_updated_by>
        <sys_updated_on>2020-07-24 04:56:39</sys_updated_on>
        <title>Keyboard/Mouse issue</title>
        <type>url</type>
        <url>6132e543db865c5099b092d8db96196f</url>
        <widget_parameters><![CDATA[{
	"link_template": {
		"value": "Circle Icon",
		"displayValue": "Circle Icon"
	}
}]]></widget_parameters>
    </sp_instance_link>
    <sys_translated_text action="DELETE" query="documentkey=2fa42947db865c5099b092d8db9619e0"/>
    <sys_update_version action="INSERT_OR_UPDATE">
        <action>DELETE</action>
        <application display_value="Coach Incident  optimization">2b20d4e8db87f3404f229a64db96199d</application>
        <file_path/>
        <instance_id>c53614fcdbfcd3c48264f70fbf9619a1</instance_id>
        <instance_name>tapestryasiadev</instance_name>
        <name>sp_instance_link_2fa42947db865c5099b092d8db9619e0</name>
        <payload>&lt;?xml version="1.0" encoding="UTF-8"?&gt;&lt;record_update table="sp_instance_link"&gt;&lt;sp_instance_link action="INSERT_OR_UPDATE"&gt;&lt;active&gt;true&lt;/active&gt;&lt;class_name/&gt;&lt;color&gt;default&lt;/color&gt;&lt;css/&gt;&lt;glyph&gt;keyboard-o&lt;/glyph&gt;&lt;id/&gt;&lt;kb_article/&gt;&lt;kb_category/&gt;&lt;kb_topic/&gt;&lt;order&gt;1&lt;/order&gt;&lt;roles/&gt;&lt;sc_cat_item/&gt;&lt;sc_category/&gt;&lt;short_description/&gt;&lt;size&gt;md&lt;/size&gt;&lt;sp_column display_value="1"&gt;27c2580cdb9e509099b092d8db96192b&lt;/sp_column&gt;&lt;sp_page/&gt;&lt;sp_widget display_value="Icon Link"&gt;3caa67afcb13020000f8d856634c9c2e&lt;/sp_widget&gt;&lt;sys_class_name&gt;sp_instance_link&lt;/sys_class_name&gt;&lt;sys_created_by&gt;admin&lt;/sys_created_by&gt;&lt;sys_created_on&gt;2020-07-21 08:16:50&lt;/sys_created_on&gt;&lt;sys_id&gt;2fa42947db865c5099b092d8db9619e0&lt;/sys_id&gt;&lt;sys_mod_count&gt;5&lt;/sys_mod_count&gt;&lt;sys_name&gt;Keyboard/Mouse issue&lt;/sys_name&gt;&lt;sys_package display_value="Coach Incident  optimization" source="x_achin_coach_inci"&gt;2b20d4e8db87f3404f229a64db96199d&lt;/sys_package&gt;&lt;sys_policy/&gt;&lt;sys_scope display_value="Coach Incident  optimization"&gt;2b20d4e8db87f3404f229a64db96199d&lt;/sys_scope&gt;&lt;sys_update_name&gt;sp_instance_link_2fa42947db865c5099b092d8db9619e0&lt;/sys_update_name&gt;&lt;sys_updated_by&gt;admin&lt;/sys_updated_by&gt;&lt;sys_updated_on&gt;2020-07-24 04:56:39&lt;/sys_updated_on&gt;&lt;title&gt;Keyboard/Mouse issue&lt;/title&gt;&lt;type&gt;url&lt;/type&gt;&lt;url&gt;6132e543db865c5099b092d8db96196f&lt;/url&gt;&lt;widget_parameters&gt;&lt;![CDATA[{
	"link_template": {
		"value": "Circle Icon",
		"displayValue": "Circle Icon"
	}
}]]&gt;&lt;/widget_parameters&gt;&lt;/sp_instance_link&gt;&lt;sys_translated_text action="delete_multiple" query="documentkey=2fa42947db865c5099b092d8db9619e0"/&gt;&lt;/record_update&gt;</payload>
        <payload_hash>1336097250</payload_hash>
        <record_name>Keyboard/Mouse issue</record_name>
        <reverted_from/>
        <source>994256bbdbcc9c90db6290c3db96192f</source>
        <source_table>sys_update_set</source_table>
        <state>previous</state>
        <sys_created_by>admin</sys_created_by>
        <sys_created_on>2020-07-24 04:56:39</sys_created_on>
        <sys_id>5ca39cc8db9e509099b092d8db9619f1</sys_id>
        <sys_mod_count>0</sys_mod_count>
        <sys_recorded_at>1737f2e2bef0000001</sys_recorded_at>
        <sys_updated_by>admin</sys_updated_by>
        <sys_updated_on>2020-07-24 04:56:39</sys_updated_on>
        <type>Instance with Link</type>
        <update_guid>14a39cc83f9e5090c3ba7a1f54aba9f1</update_guid>
        <update_guid_history>14a39cc83f9e5090c3ba7a1f54aba9f1:1336097250,e9d2540c629e5090a9e98644fb8ba3a8:594414052,394ba1cf4e865c50e97aa01845046ba3:1347303759,808ae18f2a865c50ce7c3f5ad5f7d7ff:1892706171,1f66e1c728865c50b47ef56308f8b48e:915854063,a3a4294748865c500e8edf1ee879f0e2:556007584</update_guid_history>
    </sys_update_version>
    <sys_metadata_delete action="INSERT_OR_UPDATE">
        <sys_audit_delete display_value="Record deleted 2020-07-24 13:19:36">a4e89484dbde509099b092d8db9619cf</sys_audit_delete>
        <sys_class_name>sys_metadata_delete</sys_class_name>
        <sys_created_by>admin</sys_created_by>
        <sys_created_on>2020-07-24 05:19:36</sys_created_on>
        <sys_db_object display_value="" name="sp_instance_link">sp_instance_link</sys_db_object>
        <sys_id>5d188d92ea5649e489e3d8879279b410</sys_id>
        <sys_metadata>2fa42947db865c5099b092d8db9619e0</sys_metadata>
        <sys_mod_count>0</sys_mod_count>
        <sys_name>Keyboard/Mouse issue</sys_name>
        <sys_package display_value="Coach Incident  optimization" source="x_achin_coach_inci">2b20d4e8db87f3404f229a64db96199d</sys_package>
        <sys_parent/>
        <sys_policy/>
        <sys_scope display_value="Coach Incident  optimization">2b20d4e8db87f3404f229a64db96199d</sys_scope>
        <sys_scope_delete display_value="">17e2383a57cd4729ad0ae975d0abb081</sys_scope_delete>
        <sys_update_name>sp_instance_link_2fa42947db865c5099b092d8db9619e0</sys_update_name>
        <sys_update_version display_value="sp_instance_link_2fa42947db865c5099b092d8db9619e0">5ca39cc8db9e509099b092d8db9619f1</sys_update_version>
        <sys_updated_by>admin</sys_updated_by>
        <sys_updated_on>2020-07-24 05:19:36</sys_updated_on>
    </sys_metadata_delete>
</record_update>
